caldavctl/__about__.py
caldavctl/__init__.py
caldavctl/backup.py
caldavctl/calendar_dav.py
caldavctl/cli.py
caldavctl/click_utils.py
caldavctl/config.py
caldavctl/dav.py
caldavctl/event.py
caldavctl/event_builder.py
caldavctl/ics.py
caldavctl/journal.py
caldavctl/journal_builder.py
caldavctl/object_parser.py
caldavctl/patch_click.py
caldavctl/templates.py
caldavctl/todo.py
caldavctl/utilities.py
caldavctl/utils.py
caldavctl-0.0.25.data/data/share/caldavctl/README.md
caldavctl-0.0.25.data/data/share/caldavctl/templates/base-event-template.conf
caldavctl-0.0.25.data/data/share/caldavctl/templates/calendar-nocolor.txt
caldavctl-0.0.25.data/data/share/caldavctl/templates/calendar.html
caldavctl-0.0.25.data/data/share/caldavctl/templates/calendar.txt
caldavctl-0.0.25.data/data/share/caldavctl/templates/event-fancy.html
caldavctl-0.0.25.data/data/share/caldavctl/templates/event-nocolor.txt
caldavctl-0.0.25.data/data/share/caldavctl/templates/event.html
caldavctl-0.0.25.data/data/share/caldavctl/templates/event.txt
caldavctl-0.0.25.data/data/share/caldavctl/templates/todo-nocolor.txt
caldavctl-0.0.25.data/data/share/caldavctl/templates/todo.html
caldavctl-0.0.25.data/data/share/caldavctl/templates/todo.txt
caldavctl-0.0.25.dist-info/METADATA
caldavctl-0.0.25.dist-info/WHEEL
caldavctl-0.0.25.dist-info/entry_points.txt
caldavctl-0.0.25.dist-info/licenses/LICENSE.md
caldavctl-0.0.25.dist-info/RECORD
