Metadata-Version: 2.4
Name: caldavctl
Version: 0.0.25
Summary: Command line utility to interact with CalDAV servers
Project-URL: Documentation, https://codeberg.org/hgg/caldavctl#readme
Project-URL: Issues, https://codeberg.org/hgg/caldavctl/issues
Project-URL: Source, https://codeberg.org/hgg/caldavctl
Author-email: Helder Guerreiro <helder@paxjulia.org>
License-Expression: GPL-3.0-or-later
License-File: LICENSE.md
Keywords: caldav,cli
Classifier: Development Status :: 2 - Pre-Alpha
Classifier: Programming Language :: Python
Classifier: Programming Language :: Python :: 3.12
Classifier: Programming Language :: Python :: 3.13
Classifier: Programming Language :: Python :: Implementation :: CPython
Classifier: Topic :: Office/Business :: Scheduling
Requires-Python: >=3.12
Requires-Dist: caldav==1.3.6
Requires-Dist: click==8.1.8
Requires-Dist: jinja2==3.1.5
Requires-Dist: markdown==3.8.2
Requires-Dist: platformdirs==4.3.6
Requires-Dist: requests==2.32.3
Requires-Dist: rich==14.1.0
